excel_list_transform/__init__.py
excel_list_transform/__main__.py
excel_list_transform/assert_dict_equal.py
excel_list_transform/check_indata_common.py
excel_list_transform/commontypes.py
excel_list_transform/config.py
excel_list_transform/config_auto_change_hook.py
excel_list_transform/config_enums.py
excel_list_transform/config_excel_list_transform.py
excel_list_transform/config_factory.py
excel_list_transform/config_xls_list_transf_name.py
excel_list_transform/config_xls_list_transf_num.py
excel_list_transform/file_extension.py
excel_list_transform/file_must_exist.py
excel_list_transform/generate_cfg.py
excel_list_transform/generate_txt.py
excel_list_transform/handle_csv.py
excel_list_transform/handle_empty_column.py
excel_list_transform/handle_excel.py
excel_list_transform/migrate_cfg.py
excel_list_transform/migrate_cfg_warn_hook.py
excel_list_transform/num_named_conversion.py
excel_list_transform/py.typed
excel_list_transform/recode.py
excel_list_transform/rewrite_value.py
excel_list_transform/row_split_merge.py
excel_list_transform/str_to_enum.py
excel_list_transform/transform_cmd.py
excel_list_transform/transform_func.py
excel_list_transform/transform_func_common.py
excel_list_transform/transform_func_named.py
excel_list_transform/transform_func_num.py
excel_list_transform/version_information.py
excel_list_transform-0.8.3.dist-info/licenses/LICENSE.txt
excel_list_transform-0.8.3.dist-info/METADATA
excel_list_transform-0.8.3.dist-info/WHEEL
excel_list_transform-0.8.3.dist-info/top_level.txt
excel_list_transform-0.8.3.dist-info/RECORD
