Metadata-Version: 2.4
Name: excel-list-transform
Version: 0.8.3
Summary: Transform a list in excel or CSV
Author: Tom Björkholm
Author-email: Tom Björkholm <klausuler_linnet0q@icloud.com>
Project-URL: Source code, https://bitbucket.org/tom-bjorkholm/excel-list-transform
Classifier: Programming Language :: Python :: 3
Classifier: License :: OSI Approved :: MIT License
Classifier: Operating System :: OS Independent
Requires-Python: >=3.13
License-File: LICENSE.txt
Requires-Dist: openpyxl>=3.1.5
Requires-Dist: types-openpyxl>=3.1.5.20250602
Requires-Dist: pylightxl>=1.61
Requires-Dist: XlsxWriter>=3.2.5
Requires-Dist: argcomplete>=3.6.2
Requires-Dist: pypi-simple>=1.6.1
Requires-Dist: requests>=2.32.4
Requires-Dist: types-requests>=2.32.4.20250611
Requires-Dist: packaging>=25.0
Requires-Dist: pip>=25.1.1
Requires-Dist: setuptools>=80.9.0
Requires-Dist: build>=1.2.2.post1
Requires-Dist: wheel>=0.45.1
Dynamic: author
Dynamic: license-file
Dynamic: requires-dist
Dynamic: requires-python
